{
	"title": "The Met Gala",
	"pictures": [
		{
			"imageFile": "metGala-2018/1039-cynthia-erivo.jpg",
			"title": "May 2018",
			"pictures": [
				{
					"imageFile": "metGala-2018/1039-cynthia-erivo.jpg",
					"title": "Cynthia Erivo"
				},
				{
					"imageFile": "metGala-2018/1105-amanda-seyfried.jpg",
					"title": "Amanda Seyfried"
				},
				{
					"imageFile": "metGala-2018/1201-doutzen-kroes.jpg",
					"title": "Doutzen Kroes"
				},
				{
					"imageFile": "metGala-2018/1227-lily-collins.jpg",
					"title": "Lily Collins"
				},
				{
					"imageFile": "metGala-2018/1299-bella-hadid.jpg",
					"title": "Bella Hadid"
				},
				{
					"imageFile": "metGala-2018/1400-mica-arganaraz-anja-rubik-anthony-vaccc.jpg",
					"title": "Mica Arganaraz Anja Rubik Anthony Vaccc"
				},
				{
					"imageFile": "metGala-2018/1473-kate-bosworth.jpg",
					"title": "Kate Bosworth"
				},
				{
					"imageFile": "metGala-2018/1576-mindy-kaling.jpg",
					"title": "Mindy Kaling"
				},
				{
					"imageFile": "metGala-2018/1627-uma-thurman.jpg",
					"title": "Uma Thurman"
				},
				{
					"imageFile": "metGala-2018/1688-zoe-kravitz.jpg",
					"title": "Zoe Kravitz"
				},
				{
					"imageFile": "metGala-2018/1735-brooke-shields.jpg",
					"title": "Brooke Shields"
				},
				{
					"imageFile": "metGala-2018/1764-kerry-washington.jpg",
					"title": "Kerry Washington"
				},
				{
					"imageFile": "metGala-2018/1864-corey-gamble-and-kris-jenner.jpg",
					"title": "Corey Gamble and Kris Jenner"
				},
				{
					"imageFile": "metGala-2018/1872-ashley-graham.jpg",
					"title": "Ashley Graham"
				},
				{
					"imageFile": "metGala-2018/1961-ming-xi.jpg",
					"title": "Ming Xi"
				},
				{
					"imageFile": "metGala-2018/2082-rihanna.jpg",
					"title": "Rihanna"
				},
				{
					"imageFile": "metGala-2018/2171-hailee-steinfeld.jpg",
					"title": "Hailee Steinfeld"
				},
				{
					"imageFile": "metGala-2018/225-anna-wintour.jpg",
					"title": "Anna Wintour"
				},
				{
					"imageFile": "metGala-2018/2271-diane-kruger.jpg",
					"title": "Diane Kruger"
				},
				{
					"imageFile": "metGala-2018/2289-fei-fei-sun.jpg",
					"title": "Fei Fei Sun"
				},
				{
					"imageFile": "metGala-2018/2321-lena-waithe.jpg",
					"title": "Lena Waithe"
				},
				{
					"imageFile": "metGala-2018/2361-lewis-hamilton.jpg",
					"title": "Lewis Hamilton"
				},
				{
					"imageFile": "metGala-2018/2407-lily-aldridge.jpg",
					"title": "Lily Aldridge"
				},
				{
					"imageFile": "metGala-2018/2456-kesha-ward-and-2-chainz.jpg",
					"title": "Kesha Ward and 2 Chainz"
				},
				{
					"imageFile": "metGala-2018/2490-amber-heard.jpg",
					"title": "Amber Heard"
				},
				{
					"imageFile": "metGala-2018/2580-frances-mcdormand.jpg",
					"title": "Frances Mcdormand"
				},
				{
					"imageFile": "metGala-2018/2633-ruby-rose.jpg",
					"title": "Ruby Rose"
				},
				{
					"imageFile": "metGala-2018/2653-anne-hathaway.jpg",
					"title": "Anne Hathaway"
				},
				{
					"imageFile": "metGala-2018/2676-shailene-woodley.jpg",
					"title": "Shailene Woodley"
				},
				{
					"imageFile": "metGala-2018/2726-shawn-mendes-and-hailey-baldwin.jpg",
					"title": "Shawn Mendes and Hailey Baldwin"
				},
				{
					"imageFile": "metGala-2018/2750-joan-smalls.jpg",
					"title": "Joan Smalls"
				},
				{
					"imageFile": "metGala-2018/2801-nick-cave-and-susie-bick.jpg",
					"title": "Nick Cave and Susie Bick"
				},
				{
					"imageFile": "metGala-2018/2807-sarah-paulson.jpg",
					"title": "Sarah Paulson"
				},
				{
					"imageFile": "metGala-2018/2816-donald-glover.jpg",
					"title": "Donald Glover"
				},
				{
					"imageFile": "metGala-2018/2834-michael-b-jordan.jpg",
					"title": "Michael Jordan"
				},
				{
					"imageFile": "metGala-2018/2923-ariana-grande.jpg",
					"title": "Ariana Grande"
				},
				{
					"imageFile": "metGala-2018/3034-jourdan-dunn.jpg",
					"title": "Jourdan Dunn"
				},
				{
					"imageFile": "metGala-2018/3037-taylor-hill.jpg",
					"title": "Taylor Hill"
				},
				{
					"imageFile": "metGala-2018/3180-katy-perry.jpg",
					"title": "Katy Perry"
				},
				{
					"imageFile": "metGala-2018/3227-rande-gerber-and-cindy-crawford.jpg",
					"title": "Rande Gerber and Cindy Crawford"
				},
				{
					"imageFile": "metGala-2018/3271-tom-brady-and-gisele-bundchen.jpg",
					"title": "Tom Brady and Gisele Bundchen"
				},
				{
					"imageFile": "metGala-2018/3298-greta-gerwig.jpg",
					"title": "Greta Gerwig"
				},
				{
					"imageFile": "metGala-2018/3310-jack-mccollough-laura-dern-and-lazaro-h.jpg",
					"title": "Jack Mccollough Laura Dern and Lazaro H"
				},
				{
					"imageFile": "metGala-2018/335-george-and-amal-clooney.jpg",
					"title": "George and Amal Clooney"
				},
				{
					"imageFile": "metGala-2018/3371-sarah-jessica-parker-and-andy-cohen.jpg",
					"title": "Sarah Jessica Parker and Andy Cohen"
				},
				{
					"imageFile": "metGala-2018/3414-idris-elba-and-sabrina-dhowre.jpg",
					"title": "Idris Elba and Sabrina Dhowre"
				},
				{
					"imageFile": "metGala-2018/3474-lana-del-rey-and-jared-leto.jpg",
					"title": "Lana Del Rey and Jared Leto"
				},
				{
					"imageFile": "metGala-2018/3490-nick-jonas.jpg",
					"title": "Nick Jonas"
				},
				{
					"imageFile": "metGala-2018/3503-chadwick-boseman.jpg",
					"title": "Chadwick Boseman"
				},
				{
					"imageFile": "metGala-2018/3555-priyanka-chopra.jpg",
					"title": "Priyanka Chopra"
				},
				{
					"imageFile": "metGala-2018/3603-michelle-williams.jpg",
					"title": "Michelle Williams"
				},
				{
					"imageFile": "metGala-2018/3612-alicia-vikander.jpg",
					"title": "Alicia Vikander"
				},
				{
					"imageFile": "metGala-2018/3633-laura-harrier.jpg",
					"title": "Laura Harrier"
				},
				{
					"imageFile": "metGala-2018/3650-paul-bettany-and-jennifer-connelly.jpg",
					"title": "Paul Bettany and Jennifer Connelly"
				},
				{
					"imageFile": "metGala-2018/3672-jaden-smith.jpg",
					"title": "Jaden Smith"
				},
				{
					"imageFile": "metGala-2018/3698-tessa-thompson.jpg",
					"title": "Tessa Thompson"
				},
				{
					"imageFile": "metGala-2018/3722-kendall-jenner.jpg",
					"title": "Kendall Jenner"
				},
				{
					"imageFile": "metGala-2018/3743-naomi-watts-and-michael-kors.jpg",
					"title": "Naomi Watts and Michael Kors"
				},
				{
					"imageFile": "metGala-2018/3745-mackenzie-davis.jpg",
					"title": "Mackenzie Davis"
				},
				{
					"imageFile": "metGala-2018/3759-sofia-coppola.jpg",
					"title": "Sofia Coppola"
				},
				{
					"imageFile": "metGala-2018/3820-paris-jackson-stella-mccartney-and-mile.jpg",
					"title": "Paris Jackson Stella Mccartney and Mile"
				},
				{
					"imageFile": "metGala-2018/3952-diddy-and-cassie.jpg",
					"title": "Diddy and Cassie"
				},
				{
					"imageFile": "metGala-2018/3969-letitia-wright-and-john-boyega.jpg",
					"title": "Letitia Wrighand John Boyega"
				},
				{
					"imageFile": "metGala-2018/3986-janelle-monae.jpg",
					"title": "Janelle Monae"
				},
				{
					"imageFile": "metGala-2018/401-gary-oldman-and-gisele-schmidt.jpg",
					"title": "Gary Oldman and Gisele Schmidt"
				},
				{
					"imageFile": "metGala-2018/4068-jennifer-lopez.jpg",
					"title": "Jennifer Lopez"
				},
				{
					"imageFile": "metGala-2018/4120-juliette-binoche.jpg",
					"title": "Juliette Binoche"
				},
				{
					"imageFile": "metGala-2018/4171-selena-gomez.jpg",
					"title": "Selena Gomez"
				},
				{
					"imageFile": "metGala-2018/418-daniel-kaluuya.jpg",
					"title": "Daniel Kaluuya"
				},
				{
					"imageFile": "metGala-2018/4204-yara-shahidi.jpg",
					"title": "Yara Shahidi"
				},
				{
					"imageFile": "metGala-2018/4219-gigi-hadid.jpg",
					"title": "Gigi Hadid"
				},
				{
					"imageFile": "metGala-2018/4273-travis-scott-and-kylie-jenner.jpg",
					"title": "Travis Scott and Kylie Jenner"
				},
				{
					"imageFile": "metGala-2018/4298-issa-rae.jpg",
					"title": "Issa Rae"
				},
				{
					"imageFile": "metGala-2018/4315-mary-j-blige.jpg",
					"title": "Mary Blige"
				},
				{
					"imageFile": "metGala-2018/4329-madonna.jpg",
					"title": "Madonna"
				},
				{
					"imageFile": "metGala-2018/4435-nicki-minaj.jpg",
					"title": "Nicki Minaj"
				},
				{
					"imageFile": "metGala-2018/4482-scarlett-johansson.jpg",
					"title": "Scarlett Johansson"
				},
				{
					"imageFile": "metGala-2018/4526-zendaya.jpg",
					"title": "Zendaya"
				},
				{
					"imageFile": "metGala-2018/4576-emily-ratajkowski.jpg",
					"title": "Emily Ratajkowski"
				},
				{
					"imageFile": "metGala-2018/4597-cara-delevingne.jpg",
					"title": "Cara Delevingne"
				},
				{
					"imageFile": "metGala-2018/4623-stephen-colbert-and-jimmy-fallon.jpg",
					"title": "Stephen Colbert and Jimmy Fallon"
				},
				{
					"imageFile": "metGala-2018/4671-cardi-b.jpg",
					"title": "Cardi B"
				},
				{
					"imageFile": "metGala-2018/4684-emilia-clarke.jpg",
					"title": "Emilia Clarke"
				},
				{
					"imageFile": "metGala-2018/4736-solange-knowles.jpg",
					"title": "Solange Knowles"
				},
				{
					"imageFile": "metGala-2018/4849-blake-lively.jpg",
					"title": "Blake Lively"
				},
				{
					"imageFile": "metGala-2018/508-olivia-munn.jpg",
					"title": "Olivia Munn"
				},
				{
					"imageFile": "metGala-2018/539-jasmine-sanders.jpg",
					"title": "Jasmine Sanders"
				},
				{
					"imageFile": "metGala-2018/572-luka-sabbat.jpg",
					"title": "Luka Sabbat"
				},
				{
					"imageFile": "metGala-2018/701-lili-reinhart.jpg",
					"title": "Lili Reinhart"
				},
				{
					"imageFile": "metGala-2018/737-anne-and-mitt-romney.jpg",
					"title": "Anne and Mitt Romney"
				},
				{
					"imageFile": "metGala-2018/798-rita-ora.jpg",
					"title": "Rita Ora"
				},
				{
					"imageFile": "metGala-2018/821-lynda-carter.jpg",
					"title": "Lynda Carter"
				},
				{
					"imageFile": "metGala-2018/896-donatella-versace.jpg",
					"title": "Donatella Versace"
				},
				{
					"imageFile": "metGala-2018/909-wendi-deng.jpg",
					"title": "Wendi Deng"
				},
				{
					"imageFile": "metGala-2018/939-huma-abedin.jpg",
					"title": "Huma Abedin"
				},
				{
					"imageFile": "metGala-2018/967-offset-quavo-and-takeoff-migos.jpg",
					"title": "Offset Quavo and Takeoff Migos"
				}
			]
		}
	]
}
